Workbook
Name FundSize: 'Executive Summary'!$B5
Name InvestedCapital: 'Executive Summary'!$B8
Name TotalValue: 'Executive Summary'!$B11
Name LatestNAV: 'Cash Flows'!$F22
Name LatestMOIC: 'Executive Summary'!$B$16

Sheet Executive Summary
A1: Meridian Capital Partners
A2: Fund III — Q4 2025 Portfolio Review
A4: Fund Overview
A5: Fund Size | B5: 500000000
A6: Vintage Year | B6: 2021
A7: Investment Period | B7: 2021–2024
A8: Invested Capital | B8: 385000000
A9: Realized Value | B9: 142000000
A10: Unrealized Value | B10: 498000000
A11: Total Value | B11: =B9+B10
A13: Performance
A14: Net IRR | B14: 0.218
A15: Gross IRR | B15: 0.267
A16: Net MOIC | B16: 1.66
A17: DPI (Distributions/Paid-In) | B17: =B9/B8
A18: RVPI (Residual/Paid-In) | B18: =B10/B8
A19: TVPI (Total/Paid-In) | B19: =B11/B8
A21: Portfolio Snapshot
A22: Active Companies | B22: 8
A23: Fully Exited | B23: 2
A26: Quick Navigation
A27: Fund Performance
A28: Portfolio Detail
A29: Cash Flows
A30: Scenario Analysis
A31: Sector Allocation

Sheet Fund Performance
A1: Fund Performance & Benchmarks
A2: Year | B2: Contributions | C2: Distributions | D2: Net Cash Flow | E2: Cumulative Net | F2: Net IRR | G2: MOIC | H2: Benchmark IRR
A3: 2021 | B3: -125000000 | C3: 0 | D3: =B3+C3 | E3: =D3 | F3: -0.08 | G3: 0.92 | H3: -0.05
A4: 2022 | B4: -140000000 | C4: 12000000 | D4: =B4+C4 | E4: =E3+D4 | F4: -0.03 | G4: 0.95 | H4: 0.02
A5: 2023 | B5: -85000000 | C5: 58000000 | D5: =B5+C5 | E5: =E4+D5 | F5: 0.11 | G5: 1.18 | H5: 0.09
A6: 2024 | B6: -35000000 | C6: 72000000 | D6: =B6+C6 | E6: =E5+D6 | F6: 0.19 | G6: 1.48 | H6: 0.14
A7: 2025 | B7: 0 | C7: 0 | D7: =B7+C7 | E7: =E6+D7 | F7: 0.218 | G7: 1.66 | H7: 0.16
A8: Total | B8: =SUM(B3:B7) | C8: =SUM(C3:C7) | D8: =SUM(D3:D7)

Sheet Portfolio Detail
A1: Portfolio Holdings Detail
A2: Company | B2: Sector | C2: Investment Date | D2: Cost Basis | E2: Fair Value | F2: MOIC | G2: Revenue (LTM) | H2: EBITDA (LTM) | I2: EBITDA Margin | J2: Rev Growth YoY | K2: Status | L2: Investment Thesis | M2: Watchlist
A3: Helios Energy | B3: Clean Energy | C3: 44270 | D3: 65000000 | E3: 142000000 | F3: =E3/D3 | G3: 89000000 | H3: 22000000 | I3: =H3/G3 | J3: 0.42 | K3: Active | L3: Grid-scale battery storage leader | M3: Green
A4: NovaBio Sciences | B4: Healthcare | C4: 44369 | D4: 45000000 | E4: 38000000 | F4: =E4/D4 | G4: 31000000 | H4: -2000000 | I4: =H4/G4 | J4: 0.08 | K4: Active | L4: Novel drug delivery platform | M4: Red
A5: Axion Robotics | B5: Industrials | C5: 44501 | D5: 55000000 | E5: 98000000 | F5: =E5/D5 | G5: 72000000 | H5: 18000000 | I5: =H5/G5 | J5: 0.35 | K5: Active | L5: Warehouse automation at scale | M5: Green
A6: Prism Analytics | B6: Software | C6: 44606 | D6: 40000000 | E6: 88000000 | F6: =E6/D6 | G6: 54000000 | H6: 16000000 | I6: =H6/G6 | J6: 0.55 | K6: Active | L6: AI-native business intelligence | M6: Green
A7: Stratos Logistics | B7: Logistics | C7: 44772 | D7: 35000000 | E7: 42000000 | F7: =E7/D7 | G7: 48000000 | H7: 8000000 | I7: =H7/G7 | J7: 0.18 | K7: Active | L7: Last-mile delivery optimization | M7: Yellow
A8: Cirrus Cloud | B8: Software | C8: 44822 | D8: 50000000 | E8: 105000000 | F8: =E8/D8 | G8: 68000000 | H8: 21000000 | I8: =H8/G8 | J8: 0.48 | K8: Active | L8: Multi-cloud infrastructure orchestration | M8: Green
A9: Verdant Agriculture | B9: AgTech | C9: 44936 | D9: 30000000 | E9: 27000000 | F9: =E9/D9 | G9: 19000000 | H9: 1000000 | I9: =H9/G9 | J9: 0.12 | K9: Active | L9: Precision agriculture IoT | M9: Yellow
A10: Quantum Mesh | B10: Telecom | C10: 45066 | D10: 25000000 | E10: 36000000 | F10: =E10/D10 | G10: 22000000 | H10: 5000000 | I10: =H10/G10 | J10: 0.28 | K10: Active | L10: Private 5G network solutions | M10: Green
A11: Bolt Payments | B11: Fintech | C11: 44413 | D11: 20000000 | E11: 0 | F11: =E11/D11 | G11: 0 | H11: 0 | I11: 0 | J11: 0 | K11: Written Off | L11: Real-time cross-border payments | M11: Red
A12: Apex Dynamics | B12: SaaS | C12: 44663 | D12: 20000000 | E12: 62000000 | F12: =E12/D12 | G12: 41000000 | H12: 12000000 | I12: =H12/G12 | J12: 0.62 | K12: Exited | L12: Vertical SaaS for construction | M12: Green
A13: Totals | D13: =SUM(D3:D12) | E13: =SUM(E3:E12) | F13: =E13/D13 | G13: =SUM(G3:G12) | H13: =SUM(H3:H12) | I13: =H13/G13

Sheet Cash Flows
A1: Quarterly Cash Flow Detail
A2: Quarter | B2: Contributions | C2: Distributions | D2: Net Cash Flow | E2: Cumulative Cash Flow | F2: NAV | G2: Total Return
A3: Q1 2021 | B3: -50000000 | C3: 0 | D3: =B3+C3 | E3: =D3 | F3: 48000000 | G3: =E3+F3
A4: Q2 2021 | B4: -75000000 | C4: 0 | D4: =B4+C4 | E4: =E3+D4 | F4: 118000000 | G4: =E4+F4
A5: Q3 2021 | B5: 0 | C5: 0 | D5: =B5+C5 | E5: =E4+D5 | F5: 122000000 | G5: =E5+F5
A6: Q4 2021 | B6: 0 | C6: 0 | D6: =B6+C6 | E6: =E5+D6 | F6: 115000000 | G6: =E6+F6
A7: Q1 2022 | B7: -60000000 | C7: 0 | D7: =B7+C7 | E7: =E6+D7 | F7: 168000000 | G7: =E7+F7
A8: Q2 2022 | B8: -45000000 | C8: 0 | D8: =B8+C8 | E8: =E7+D8 | F8: 210000000 | G8: =E8+F8
A9: Q3 2022 | B9: -35000000 | C9: 12000000 | D9: =B9+C9 | E9: =E8+D9 | F9: 235000000 | G9: =E9+F9
A10: Q4 2022 | B10: 0 | C10: 0 | D10: =B10+C10 | E10: =E9+D10 | F10: 228000000 | G10: =E10+F10
A11: Q1 2023 | B11: -40000000 | C11: 18000000 | D11: =B11+C11 | E11: =E10+D11 | F11: 278000000 | G11: =E11+F11
A12: Q2 2023 | B12: -15000000 | C12: 0 | D12: =B12+C12 | E12: =E11+D12 | F12: 295000000 | G12: =E12+F12
A13: Q3 2023 | B13: -30000000 | C13: 20000000 | D13: =B13+C13 | E13: =E12+D13 | F13: 340000000 | G13: =E13+F13
A14: Q4 2023 | B14: 0 | C14: 20000000 | D14: =B14+C14 | E14: =E13+D14 | F14: 365000000 | G14: =E14+F14
A15: Q1 2024 | B15: -20000000 | C15: 25000000 | D15: =B15+C15 | E15: =E14+D15 | F15: 410000000 | G15: =E15+F15
... A22: Q4 2025 | B22: 0 | C22: 0 | D22: =B22+C22 | E22: =E21+D22 | F22: 640000000 | G22: =E22+F22
A23: Total | B23: =SUM(B3:B22) | C23: =SUM(C3:C22) | D23: =SUM(D3:D22) | G23: =G22

Sheet Scenario Analysis
A1: Portfolio Scenario Analysis
A3: Assumptions
A4: Assumption | B4: Base | C4: Bull | D4: Bear
A5: Revenue Growth | B5: 0.25 | C5: 0.4 | D5: 0.1
A6: EBITDA Margin Expansion | B6: 0.02 | C6: 0.05 | D6: -0.03
A7: Multiple Expansion | B7: 0 | C7: 0.03 | D7: -0.05
A8: Exit Timeline (years) | B8: 3 | C8: 2 | D8: 5
A9: Loss Rate | B9: 0.05 | C9: 0.02 | D9: 0.15
A11: Projected Outcomes
A12: Metric | B12: Base | C12: Bull | D12: Bear
A13: Portfolio Revenue | B13: ='Portfolio Detail'!G13*(1+B5) | C13: ='Portfolio Detail'!G13*(1+C5) | D13: ='Portfolio Detail'!G13*(1+D5)
A14: Portfolio EBITDA | B14: =B13*('Portfolio Detail'!I13+B6) | C14: =C13*('Portfolio Detail'!I13+C6) | D14: =D13*('Portfolio Detail'!I13+D6)
A15: Implied EV (12x EBITDA) | B15: =B14*12 | C15: =C14*12 | D15: =D14*12
A16: Loss Adjustment | B16: =B15*(-B9) | C16: =C15*(-C9) | D16: =D15*(-D9)
A17: Net Portfolio Value | B17: =B15+B16 | C17: =C15+C16 | D17: =D15+D16
A18: Implied MOIC | B18: =B17/'Executive Summary'!B8 | C18: =C17/'Executive Summary'!B8 | D18: =D17/'Executive Summary'!B8
F30: Base | G30: Bull | H30: Bear

Sheet Sector Allocation
A1: Sector Allocation Analysis
A2: Sector | B2: # Companies | C2: Total Cost Basis | D2: Total Fair Value | E2: Sector MOIC
A3: Software | B3: 2 | C3: 90000000 | D3: 193000000 | E3: =D3/C3
A4: Clean Energy | B4: 1 | C4: 65000000 | D4: 142000000 | E4: =D4/C4
A5: Healthcare | B5: 1 | C5: 45000000 | D5: 38000000 | E5: =D5/C5
A6: Industrials | B6: 1 | C6: 55000000 | D6: 98000000 | E6: =D6/C6
A7: Logistics | B7: 1 | C7: 35000000 | D7: 42000000 | E7: =D7/C7
A8: AgTech | B8: 1 | C8: 30000000 | D8: 27000000 | E8: =D8/C8
A9: Telecom | B9: 1 | C9: 25000000 | D9: 36000000 | E9: =D9/C9
A10: Fintech | B10: 1 | C10: 20000000 | D10: 0 | E10: =D10/C10
